setup.py
bunia/__init__.py
bunia/discovery.py
bunia.egg-info/PKG-INFO
bunia.egg-info/SOURCES.txt
bunia.egg-info/dependency_links.txt
bunia.egg-info/top_level.txt
bunia/api/__init__.py
bunia/api/args.py
bunia/api/command.py
bunia/output/__init__.py
bunia/output/base.py
bunia/output/cons.py
bunia/runner/__init__.py
bunia/runner/base.py
bunia/runner/console.py
bunia/runner/html.py
bunia/runner/inline.py